DifferentialAlgebra.cpython-38-x86_64-linux-gnu.so
differentialalgebra-5.3.dist-info/LICENSE
differentialalgebra-5.3.dist-info/METADATA
differentialalgebra-5.3.dist-info/WHEEL
differentialalgebra-5.3.dist-info/top_level.txt
differentialalgebra-5.3.dist-info/RECORD
